LICENSE
MANIFEST.in
README.rst
setup.py
sci/__init__.py
sci/compute.py
sci/db.py
sci/fh.py
sci/json.py
sci/new.py
sci/old.py
sci/store.py
sci/tools.py
sci.egg-info/PKG-INFO
sci.egg-info/SOURCES.txt
sci.egg-info/dependency_links.txt
sci.egg-info/requires.txt
sci.egg-info/top_level.txt