Metadata-Version: 1.1
Name: sci
Version: 0.1.5
Summary: a collection of convenience and wrapper functions supporting tasks frequently needed by scientists
Home-page: https://github.com/FredHutch/sci-package
Author: Dirk Petersen
Author-email: dp@nowhere.com
License: UNKNOWN
Download-URL: https://github.com/FredHutch/sci-package/tarball/0.1.5
Keywords: hpc,scientific computing
Platform: UNKNOWN
Classifier: Development Status :: 4 - Beta
Classifier: Environment :: Console
Classifier: Intended Audience :: Developers
Classifier: Intended Audience :: Science/Research
Classifier: Intended Audience :: System Administrators
Classifier: License :: OSI Approved :: Apache Software License
Classifier: Natural Language :: English
Classifier: Operating System :: POSIX :: Linux
Classifier: Programming Language :: Python :: 3
Classifier: Programming Language :: Python :: 3.5
Classifier: Programming Language :: Python :: 3.6
Classifier: Programming Language :: Python :: 3.7
Classifier: Programming Language :: Python :: Implementation :: CPython
Classifier: Programming Language :: Unix Shell
Classifier: Topic :: Software Development :: Libraries :: Python Modules
Classifier: Topic :: System :: Systems Administration
Classifier: Topic :: Utilities
